pydantic_meta/__init__.py
pydantic_meta/_validators.py
pydantic_meta/partial.py
pydantic_meta/pick.py
pydantic_meta/required.py
pydantic_meta-0.3.3.dist-info/METADATA
pydantic_meta-0.3.3.dist-info/WHEEL
pydantic_meta-0.3.3.dist-info/RECORD
