Metadata-Version: 2.1
Name: pydantic-meta
Version: 0.3.3
Summary: 
Author: VitailOG
Author-email: vzaharkiv28@gmail.com
Requires-Python: >=3.10,<4.0
Classifier: Programming Language :: Python :: 3
Classifier: Programming Language :: Python :: 3.10
Classifier: Programming Language :: Python :: 3.11
Requires-Dist: pydantic (>=1.10.4,<2.0.0)
Requires-Dist: pytest (>=7.2.2,<8.0.0)
